3           0 LOAD_CONST               1 ('S')
              2 STORE_FAST               1 (xorKey)

  4           4 LOAD_GLOBAL              0 (len)
              6 LOAD_FAST                0 (inpString)
              8 CALL_FUNCTION            1
             10 STORE_FAST               2 (length)

  5          12 LOAD_GLOBAL              1 (range)
             14 LOAD_FAST                2 (length)
             16 CALL_FUNCTION            1
             18 GET_ITER
        >>   20 FOR_ITER                56 (to 78)
             22 STORE_FAST               3 (i)

  6          24 LOAD_FAST                0 (inpString)
             26 LOAD_CONST               0 (None)
             28 LOAD_FAST                3 (i)
             30 BUILD_SLICE              2
             32 BINARY_SUBSCR
             34 LOAD_GLOBAL              2 (chr)
             36 LOAD_GLOBAL              3 (ord)
             38 LOAD_FAST                0 (inpString)
             40 LOAD_FAST                3 (i)
             42 BINARY_SUBSCR
             44 CALL_FUNCTION            1
             46 LOAD_GLOBAL              3 (ord)
             48 LOAD_FAST                1 (xorKey)
             50 CALL_FUNCTION            1
             52 BINARY_XOR
             54 CALL_FUNCTION            1
             56 BINARY_ADD
             58 LOAD_FAST                0 (inpString)
             60 LOAD_FAST                3 (i)
             62 LOAD_CONST               2 (1)
             64 BINARY_ADD
             66 LOAD_CONST               0 (None)
             68 BUILD_SLICE              2
             70 BINARY_SUBSCR
             72 BINARY_ADD
             74 STORE_FAST               0 (inpString)
             76 JUMP_ABSOLUTE           20

  9     >>   78 LOAD_FAST                0 (inpString)
             80 RETURN_VALUE